neurocarto/__init__.py
neurocarto/__main__.py
neurocarto/config.py
neurocarto/files.py
neurocarto/main_app.py
neurocarto/main_index.py
neurocarto/probe.py
neurocarto/probe_npx/__init__.py
neurocarto/probe_npx/desp.py
neurocarto/probe_npx/io.py
neurocarto/probe_npx/meta.py
neurocarto/probe_npx/npx.py
neurocarto/probe_npx/plot.py
neurocarto/probe_npx/select.py
neurocarto/probe_npx/select_default.py
neurocarto/probe_npx/select_random.py
neurocarto/probe_npx/select_weaker.py
neurocarto/probe_npx/select_weaker_debug.py
neurocarto/probe_npx/stat.py
neurocarto/probe_npx/utils.py
neurocarto/probe_npx/views.py
neurocarto/util/__init__.py
neurocarto/util/atlas_brain.py
neurocarto/util/atlas_slice.py
neurocarto/util/atlas_struct.py
neurocarto/util/bokeh_app.py
neurocarto/util/bokeh_util.py
neurocarto/util/debug.py
neurocarto/util/probe_coor.py
neurocarto/util/util_blueprint.py
neurocarto/util/util_numpy.py
neurocarto/util/utils.py
neurocarto/util/edit/__init__.py
neurocarto/util/edit/_actions.py
neurocarto/util/edit/actions.py
neurocarto/util/edit/atlas.py
neurocarto/util/edit/category.py
neurocarto/util/edit/checking.py
neurocarto/util/edit/clustering.py
neurocarto/util/edit/data.py
neurocarto/util/edit/debug.py
neurocarto/util/edit/moving.py
neurocarto/util/edit/optimize.py
neurocarto/util/edit/plot.py
neurocarto/util/edit/probe.py
neurocarto/util/edit/script.py
neurocarto/util/edit/surrounding.py
neurocarto/views/__init__.py
neurocarto/views/atlas.py
neurocarto/views/base.py
neurocarto/views/blueprint.py
neurocarto/views/blueprint_script.py
neurocarto/views/data.py
neurocarto/views/data_density.py
neurocarto/views/image.py
neurocarto/views/image_npy.py
neurocarto/views/image_plt.matplotlibrc
neurocarto/views/image_plt.py
neurocarto/views/probe.py
neurocarto/views/record.py
neurocarto/views/utils.py
neurocarto/views/view_efficient.py
neurocarto-0.1.0.dist-info/LICENSE
neurocarto-0.1.0.dist-info/METADATA
neurocarto-0.1.0.dist-info/WHEEL
neurocarto-0.1.0.dist-info/entry_points.txt
neurocarto-0.1.0.dist-info/top_level.txt
neurocarto-0.1.0.dist-info/RECORD
