Metadata-Version: 2.2
Name: neurocarto
Version: 0.1.0
Summary: A web-interface channelmap editor for Neuropixels probe familiy
Author-email: Ta-Shun Su <antoniost29@gmail.com>
License: BSD 3-Clause License
Project-URL: Homepage, https://github.com/AntonioST/NeuroCarto
Project-URL: Documentation, https://neurocarto.readthedocs.io/en/latest/
Project-URL: Repository, https://github.com/AntonioST/NeuroCarto
Project-URL: Issues, https://github.com/AntonioST/NeuroCarto/issues
Keywords: Electrophysiology,Neuropixels,Channelmap
Classifier: Development Status :: 3 - Alpha
Classifier: Programming Language :: Python
Classifier: Programming Language :: Python :: 3
Classifier: Programming Language :: Python :: 3 :: Only
Classifier: Programming Language :: Python :: 3.10
Classifier: License :: OSI Approved :: BSD License
Classifier: Natural Language :: English
Classifier: Operating System :: OS Independent
Classifier: Environment :: Web Environment
Classifier: Environment :: Console
Classifier: Topic :: Scientific/Engineering
Classifier: Intended Audience :: Science/Research
Classifier: Typing :: Typed
Requires-Python: >=3.10
License-File: LICENSE
Requires-Dist: numpy
Requires-Dist: scipy
Requires-Dist: matplotlib
Requires-Dist: typing_extensions
Requires-Dist: bokeh
Provides-Extra: full
Requires-Dist: probeinterface; extra == "full"
Requires-Dist: brainglobe-atlasapi; extra == "full"
Requires-Dist: Pillow; extra == "full"
Requires-Dist: tifffile; extra == "full"
Requires-Dist: pandas; extra == "full"
Requires-Dist: polars; extra == "full"
Provides-Extra: doc
Requires-Dist: sphinx; extra == "doc"
Requires-Dist: jupyter; extra == "doc"
Requires-Dist: jupyter_contrib_nbextensions; extra == "doc"
Requires-Dist: nbsphinx; extra == "doc"
Requires-Dist: sphinx-rtd-theme; extra == "doc"
Requires-Dist: sphinx-markdown-builder; extra == "doc"
